mathlang/__init__.py
mathlang-0.0.1.dist-info/LICENSE
mathlang-0.0.1.dist-info/METADATA
mathlang-0.0.1.dist-info/WHEEL
mathlang-0.0.1.dist-info/top_level.txt
mathlang-0.0.1.dist-info/RECORD
